helmeos/__init__.py
helmeos/example.py
helmeos/helm_table.py
helmeos/phys_const.py
helmeos/table_param.py
helmeos-1.0.0.dist-info/LICENSE
helmeos-1.0.0.dist-info/METADATA
helmeos-1.0.0.dist-info/WHEEL
helmeos-1.0.0.dist-info/top_level.txt
helmeos-1.0.0.dist-info/RECORD
