Metadata-Version: 2.1
Name: helmeos
Version: 1.0.0
Summary: A Python implementation/port of Frank Timmes' Helmholtz EoS.
Author-email: "Matthew S. B. Coleman" <msbc@princeton.edu>
Maintainer-email: "Matthew S. B. Coleman" <msbc@princeton.edu>
License: MIT License
Project-URL: Repository, https://github.com/msbc/helmeos
Keywords: equation of state,helmeos,eos,thermodynamics,astrophysics,astronomy,physics
Classifier: License :: OSI Approved :: MIT License
Classifier: Programming Language :: Python :: 3
Classifier: Intended Audience :: Science/Research
Classifier: Topic :: Scientific/Engineering :: Astronomy
Classifier: Topic :: Scientific/Engineering :: Physics
License-File: LICENSE
Requires-Dist: numpy
Provides-Extra: plotting
Requires-Dist: matplotlib; extra == "plotting"
